Metadata-Version: 2.4
Name: llama-index-multi-modal-llms-huggingface
Version: 0.5.1
Summary: llama-index multi_modal_llms HuggingFace integration by [Cihan Yalçın](https://www.linkedin.com/in/chanyalcin/)
Author-email: "M.Cihan Yalçın" <mcihan.yalcin@outlook.com>
License-Expression: MIT
License-File: LICENSE
Requires-Python: <4.0,>=3.10
Requires-Dist: llama-index-core<0.15,>=0.13.0
Requires-Dist: llama-index-llms-huggingface<1,>=0.5.0
Requires-Dist: pillow>=10.0.0
Requires-Dist: qwen-vl-utils>=0.0.8
Requires-Dist: torchvision>=0.19.1
Requires-Dist: transformers[torch]>=4.45
